ruspy-0.1.1.dist-info/METADATA
ruspy-0.1.1.dist-info/WHEEL
ruspy-0.1.1.dist-info/license_files/LICENSE
ruspy/__init__.py
ruspy/ruspy.abi3.so
ruspy-0.1.1.dist-info/RECORD
