Metadata-Version: 2.1
Name: ruspy
Version: 0.1.1
Classifier: Programming Language :: Rust
Classifier: Operating System :: POSIX :: Linux
License-File: LICENSE
Summary: Data analysis powered by Rust
Author: Manas Verma <manas.verma@gmail.com>
Author-email: Manas Verma <manas.verma@gmail.com>
Requires-Python: >=3.7
